{
  "@context": [
    "https://w3id.org/ixo/context/v1",
    {
      "@base": "https://w3id.org/ixo/protocol/group-types/v1"
    }
  ],
  "@graph": [
    {
      "@id": "https://w3id.org/ixo/protocol/group-types/v1",
      "@type": "skos:ConceptScheme",
      "dcterms:title": "IXO Group Types",
      "dcterms:description": "Kinds of governance group within a DAO or organisation.",
      "dcterms:created": "2026-06-04",
      "dcterms:source": "legacy ixofoundation/ns protocol/tags groupType (rebuilt as SKOS)",
      "skos:hasTopConcept": [
        {
          "@id": "#membership"
        },
        {
          "@id": "#custodians"
        },
        {
          "@id": "#security"
        },
        {
          "@id": "#finance"
        },
        {
          "@id": "#operations"
        }
      ]
    },
    {
      "@id": "#membership",
      "@type": "skos:Concept",
      "skos:inScheme": {
        "@id": "https://w3id.org/ixo/protocol/group-types/v1"
      },
      "skos:prefLabel": {
        "@value": "Membership",
        "@language": "en"
      },
      "skos:definition": {
        "@value": "The primary governance body that proposes and votes on all high-level decisions, including the creation and oversight of specialised committees.",
        "@language": "en"
      },
      "skos:notation": "membership",
      "skos:topConceptOf": {
        "@id": "https://w3id.org/ixo/protocol/group-types/v1"
      }
    },
    {
      "@id": "#custodians",
      "@type": "skos:Concept",
      "skos:inScheme": {
        "@id": "https://w3id.org/ixo/protocol/group-types/v1"
      },
      "skos:prefLabel": {
        "@value": "Custodians",
        "@language": "en"
      },
      "skos:definition": {
        "@value": "A long-lived multisig council of trusted community stewards empowered to safeguard the chain's best interests and block malicious or harmful actions.",
        "@language": "en"
      },
      "skos:notation": "custodians",
      "skos:topConceptOf": {
        "@id": "https://w3id.org/ixo/protocol/group-types/v1"
      }
    },
    {
      "@id": "#security",
      "@type": "skos:Concept",
      "skos:inScheme": {
        "@id": "https://w3id.org/ixo/protocol/group-types/v1"
      },
      "skos:prefLabel": {
        "@value": "Security",
        "@language": "en"
      },
      "skos:definition": {
        "@value": "A committee of elected security specialists who monitor, triage, and respond to vulnerabilities affecting the Impact Hub, acting swiftly while remaining accountable to the membership DAO.",
        "@language": "en"
      },
      "skos:notation": "security",
      "skos:topConceptOf": {
        "@id": "https://w3id.org/ixo/protocol/group-types/v1"
      }
    },
    {
      "@id": "#finance",
      "@type": "skos:Concept",
      "skos:inScheme": {
        "@id": "https://w3id.org/ixo/protocol/group-types/v1"
      },
      "skos:prefLabel": {
        "@value": "Finance",
        "@language": "en"
      },
      "skos:definition": {
        "@value": "An elected treasury team responsible for managing funds, processing approved claim payouts, and providing transparent on-chain financial reporting.",
        "@language": "en"
      },
      "skos:notation": "finance",
      "skos:topConceptOf": {
        "@id": "https://w3id.org/ixo/protocol/group-types/v1"
      }
    },
    {
      "@id": "#operations",
      "@type": "skos:Concept",
      "skos:inScheme": {
        "@id": "https://w3id.org/ixo/protocol/group-types/v1"
      },
      "skos:prefLabel": {
        "@value": "Operations",
        "@language": "en"
      },
      "skos:definition": {
        "@value": "An elected operations desk that executes day-to-day tasks and implements actions ratified through governance, ensuring smooth organisational workflows.",
        "@language": "en"
      },
      "skos:notation": "operations",
      "skos:topConceptOf": {
        "@id": "https://w3id.org/ixo/protocol/group-types/v1"
      }
    }
  ]
}
